bayessynth/__init__.py
bayessynth/analysis/__init__.py
bayessynth/analysis/readtrace.py
bayessynth/analysis/summarizefactors.py
bayessynth/analysis/summarizeppc.py
bayessynth/modeling/__init__.py
bayessynth/modeling/fit.py
bayessynth/plots/__init__.py
bayessynth/plots/plotfactors.py
bayessynth/plots/plotppc.py
bayessynth/plots/plotppcbell.py
bayessynth/plots/plotppcdiff.py
bayessynth-0.1.dist-info/LICENSE
bayessynth-0.1.dist-info/METADATA
bayessynth-0.1.dist-info/WHEEL
bayessynth-0.1.dist-info/top_level.txt
bayessynth-0.1.dist-info/RECORD
