Metadata-Version: 2.1
Name: bayessynth
Version: 0.1
Summary: Python implementation of Bayesian Synthetic Controls
Home-page: https://github.com/eliastuo/bayessynth
Author: Elias Tuomaala
Author-email: mail@eliastuomaala.com
License: MIT
Platform: UNKNOWN
Classifier: Programming Language :: Python :: 3
Classifier: License :: OSI Approved :: MIT License
Classifier: Operating System :: OS Independent
Requires-Python: >=3.7.4
